jasmin_realtime/__init__.py
jasmin_realtime/__main__.py
jasmin_realtime/amqp0-9-1.xml
jasmin_realtime/jasmin_realtime
jasmin_realtime/realtime/__init__.py
jasmin_realtime/realtime/biller.py
jasmin_realtime/realtime/logger.py
jasmin_realtime/realtime/main.py
jasmin_realtime/realtime/moduler.py
jasmin_realtime/realtime/sources.py
jasmin_realtime-0.1.0.dist-info/METADATA
jasmin_realtime-0.1.0.dist-info/WHEEL
jasmin_realtime-0.1.0.dist-info/licenses/LICENSE
jasmin_realtime-0.1.0.dist-info/RECORD
